{
  "${modID}:ExampleCard": {
    "NAME": "Name",
    "DESCRIPTION": "Description.",
    "UPGRADE_DESCRIPTION": "If you change the constructor of your card to use super(cardInfo, true); this will be the card's description when it is upgraded.",
    "EXTENDED_DESCRIPTION": [
      "You can put more text in here.",
      "If you need to use it for stuff.",
      "Blizzard is a good example for this."
    ]
  },

  "${modID}:Strike": {
    "NAME": "打击",
    "DESCRIPTION": "造成!D!点伤害",
    "UPGRADE_DESCRIPTION": "造成!D!点伤害",
    "EXTENDED_DESCRIPTION": [
      "螺丝刀",
      "草莓猫",
      "装扮"
    ]
  }
}
